confseq/__init__.py
confseq/betting.py
confseq/betting_strategies.py
confseq/boundaries.pypy38-pp73-darwin.so
confseq/conjmix_bounded.py
confseq/cs_plots.py
confseq/misc.py
confseq/other_bounded.py
confseq/predmix.py
confseq/quantiles.pypy38-pp73-darwin.so
confseq/types.py
confseq-0.0.11.dist-info/LICENSE
confseq-0.0.11.dist-info/METADATA
confseq-0.0.11.dist-info/WHEEL
confseq-0.0.11.dist-info/top_level.txt
confseq-0.0.11.dist-info/RECORD
