Metadata-Version: 2.1
Name: confseq
Version: 0.0.11
Summary: Confidence sequences and uniform boundaries
Home-page: https://github.com/gostevehoward/confseq
Author: Steve Howard
Author-email: dev@gostevehoward.com
Classifier: Programming Language :: Python :: 3
Classifier: Programming Language :: C++
Classifier: License :: OSI Approved :: MIT License
Classifier: Operating System :: OS Independent
Classifier: Development Status :: 3 - Alpha
Classifier: Intended Audience :: Science/Research
Classifier: Programming Language :: Python :: Implementation :: CPython
Classifier: Programming Language :: Python :: Implementation :: PyPy
Classifier: Topic :: Scientific/Engineering :: Mathematics
License-File: LICENSE
Requires-Dist: pybind11 (>=2.3)
Requires-Dist: numpy
Requires-Dist: matplotlib
Requires-Dist: multiprocess
Requires-Dist: scipy
Requires-Dist: pytest
Requires-Dist: pandas
